crpyt/__init__.py
crpyt/cli.py
crpyt/encryption.py
crpyt-0.0.2.dist-info/LICENSE-APACHE.md
crpyt-0.0.2.dist-info/LICENSE-MIT.md
crpyt-0.0.2.dist-info/METADATA
crpyt-0.0.2.dist-info/WHEEL
crpyt-0.0.2.dist-info/entry_points.txt
crpyt-0.0.2.dist-info/top_level.txt
crpyt-0.0.2.dist-info/RECORD
