Metadata-Version: 2.1
Name: crpyt
Version: 0.0.2
Summary: Encrypt files within a tree using GPG
Home-page: https://github.com/MolassesLover/Crpyt
Author: MolassesLover
Author-email: 60114762+MolassesLover@users.noreply.github.com
License: MIT
License-File: LICENSE-APACHE.md
License-File: LICENSE-MIT.md
